[
    {
        "phone": "+62 802 186 0497",
        "salary": "3415.39"
    },
    {
        "phone": "+502 517 799 1156",
        "salary": "3526.52"
    },
    {
        "phone": "+86 960 881 3426",
        "salary": "4542.73"
    },
    {
        "phone": "+48 233 965 1521",
        "salary": "5584.10"
    },
    {
        "phone": "+66 481 234 9694",
        "salary": "5738.87"
    },
    {
        "phone": "+966 244 318 7293",
        "salary": "3203.97"
    },
    {
        "phone": "+33 730 812 6195",
        "salary": "4368.25"
    },
    {
        "phone": "+358 464 527 6415",
        "salary": "5086.32"
    },
    {
        "phone": "+86 269 859 6186",
        "salary": "5001.41"
    },
    {
        "phone": "+63 745 783 6957",
        "salary": "3495.53"
    },
    {
        "phone": "+30 924 374 3641",
        "salary": "4095.64"
    },
    {
        "phone": "+66 587 596 0827",
        "salary": "4966.70"
    },
    {
        "phone": "+52 424 827 1714",
        "salary": "4536.44"
    },
    {
        "phone": "+62 268 208 4937",
        "salary": "4738.46"
    },
    {
        "phone": "+48 431 877 2627",
        "salary": "3410.23"
    },
    {
        "phone": "+30 723 866 0450",
        "salary": "5017.62"
    },
    {
        "phone": "+234 515 435 2936",
        "salary": "4214.92"
    },
    {
        "phone": "+375 467 170 1049",
        "salary": "3538.52"
    },
    {
        "phone": "+234 539 576 2785",
        "salary": "4185.51"
    },
    {
        "phone": "+7 269 295 9729",
        "salary": "4763.16"
    }
]